chizhik_api/__init__.py
chizhik_api/manager.py
chizhik_api/endpoints/advertising.py
chizhik_api/endpoints/catalog.py
chizhik_api/endpoints/general.py
chizhik_api/endpoints/geolocation.py
chizhik_api-0.2.3.dist-info/licenses/LICENSE
chizhik_api-0.2.3.dist-info/METADATA
chizhik_api-0.2.3.dist-info/WHEEL
chizhik_api-0.2.3.dist-info/top_level.txt
chizhik_api-0.2.3.dist-info/RECORD
