Metadata-Version: 2.4
Name: chizhik_api
Version: 0.2.3
Summary: A Python API client for Chizhik catalog
Author: Miskler
License-Expression: MIT
Project-URL: Homepage, https://github.com/Open-Inflation/chizhik_api
Project-URL: Repository, https://github.com/Open-Inflation/chizhik_api
Project-URL: Documentation, https://open-inflation.github.io/chizhik_api/quick_start
Keywords: api,chizhik,store,catalog
Classifier: Programming Language :: Python :: 3
Classifier: Programming Language :: Python :: 3.10
Classifier: Programming Language :: Python :: 3.11
Classifier: Programming Language :: Python :: 3.12
Classifier: Programming Language :: Python :: 3.13
Classifier: Operating System :: Microsoft :: Windows
Classifier: Operating System :: POSIX :: Linux
Classifier: Intended Audience :: Developers
Classifier: Intended Audience :: Information Technology
Classifier: Topic :: Software Development :: Libraries :: Python Modules
Classifier: Topic :: Internet
Classifier: Topic :: Utilities
Requires-Python: >=3.10
License-File: LICENSE
Requires-Dist: camoufox[geoip]
Requires-Dist: human_requests
Requires-Dist: aiohttp
Requires-Dist: aiohttp-retry
Provides-Extra: tests
Requires-Dist: pytest; extra == "tests"
Requires-Dist: pytest-anyio; extra == "tests"
Requires-Dist: pytest-jsonschema-snapshot; extra == "tests"
Requires-Dist: jsoncrack-for-sphinx; extra == "tests"
Dynamic: license-file
